kubeflow/__init__.py
kubeflow/py.typed
kubeflow/common/__init__.py
kubeflow/common/constants.py
kubeflow/common/types.py
kubeflow/common/utils.py
kubeflow/optimizer/__init__.py
kubeflow/optimizer/api/__init__.py
kubeflow/optimizer/api/optimizer_client.py
kubeflow/optimizer/backends/__init__.py
kubeflow/optimizer/backends/base.py
kubeflow/optimizer/backends/kubernetes/__init__.py
kubeflow/optimizer/backends/kubernetes/backend.py
kubeflow/optimizer/backends/kubernetes/utils.py
kubeflow/optimizer/constants/__init__.py
kubeflow/optimizer/constants/constants.py
kubeflow/optimizer/types/__init__.py
kubeflow/optimizer/types/algorithm_types.py
kubeflow/optimizer/types/optimization_types.py
kubeflow/optimizer/types/search_types.py
kubeflow/trainer/__init__.py
kubeflow/trainer/api/__init__.py
kubeflow/trainer/api/trainer_client.py
kubeflow/trainer/api/trainer_client_test.py
kubeflow/trainer/backends/__init__.py
kubeflow/trainer/backends/base.py
kubeflow/trainer/backends/container/backend.py
kubeflow/trainer/backends/container/backend_test.py
kubeflow/trainer/backends/container/runtime_loader.py
kubeflow/trainer/backends/container/runtime_loader_test.py
kubeflow/trainer/backends/container/types.py
kubeflow/trainer/backends/container/utils.py
kubeflow/trainer/backends/container/adapters/base.py
kubeflow/trainer/backends/container/adapters/docker.py
kubeflow/trainer/backends/container/adapters/podman.py
kubeflow/trainer/backends/kubernetes/__init__.py
kubeflow/trainer/backends/kubernetes/backend.py
kubeflow/trainer/backends/kubernetes/backend_test.py
kubeflow/trainer/backends/kubernetes/constants.py
kubeflow/trainer/backends/kubernetes/utils.py
kubeflow/trainer/backends/kubernetes/utils_test.py
kubeflow/trainer/backends/localprocess/__init__.py
kubeflow/trainer/backends/localprocess/backend.py
kubeflow/trainer/backends/localprocess/backend_test.py
kubeflow/trainer/backends/localprocess/constants.py
kubeflow/trainer/backends/localprocess/job.py
kubeflow-0.3.0.dist-info/METADATA
kubeflow-0.3.0.dist-info/WHEEL
kubeflow-0.3.0.dist-info/licenses/LICENSE
kubeflow-0.3.0.dist-info/RECORD
