Metadata-Version: 2.4
Name: kubeflow
Version: 0.3.0
Summary: Kubeflow Python SDK to manage ML workloads and to interact with Kubeflow APIs.
Project-URL: Homepage, https://github.com/kubeflow/sdk
Project-URL: Documentation, https://www.kubeflow.org/docs/components
Project-URL: Source, https://github.com/kubeflow/sdk
Author-email: The Kubeflow Authors <kubeflow-discuss@googlegroups.com>
License-Expression: Apache-2.0
License-File: LICENSE
Keywords: ai,kubeflow,llm,model training,trainer
Classifier: Intended Audience :: Developers
Classifier: Intended Audience :: Education
Classifier: Intended Audience :: Science/Research
Classifier: License :: OSI Approved :: Apache Software License
Classifier: Operating System :: OS Independent
Classifier: Programming Language :: Python :: 3.9
Classifier: Programming Language :: Python :: 3.10
Classifier: Programming Language :: Python :: 3.11
Classifier: Topic :: Scientific/Engineering
Classifier: Topic :: Scientific/Engineering :: Artificial Intelligence
Classifier: Topic :: Software Development
Classifier: Topic :: Software Development :: Libraries
Classifier: Topic :: Software Development :: Libraries :: Python Modules
Requires-Python: >=3.9
Requires-Dist: kubeflow-katib-api>=0.19.0
Requires-Dist: kubeflow-trainer-api>=2.0.0
Requires-Dist: kubernetes>=27.2.0
Requires-Dist: pydantic>=2.10.0
Provides-Extra: docker
Requires-Dist: docker>=6.1.3; extra == 'docker'
Provides-Extra: podman
Requires-Dist: podman>=5.6.0; extra == 'podman'
